Metadata-Version: 2.1
Name: dev-fenics-fiat
Version: 2019.2.1
Summary: FInite element Automatic Tabulator
Home-page: https://bitbucket.org/fenics-project/fiat/
Download-URL: https://bitbucket.org/fenics-project/fiat/downloads/fenics-fiat-2019.2.1.tar.gz
Author: Robert C. Kirby et al.
Author-email: fenics-dev@googlegroups.com
License: LGPL v3 or later
Platform: UNKNOWN
License-File: COPYING
License-File: COPYING.LESSER
License-File: AUTHORS
Requires-Dist: numpy
Requires-Dist: sympy
